{
  "id": 128918407,
  "title": "Vinhomes SmartCity - Quỹ căn thuê cập nhật tháng 12/2025",
  "description": "Ký hợp đồng chính chủ.\nPháp lý rõ ràng.\nMiễn phí xem nhà.\n\nCăn studio 25m² - 32m²- 34m2\nNguyên bản ( rèm, giàn phơi, nóng lạnh, điều hoà) 5.5-6tr\nĐồ cơ bản ( bếp, tủ bếp, điều hoà, nóng lạnh, tủ quần áo) : 6,5tr\nFull đồ 7tr - 8tr/tháng\n\nCăn 1PN 43m² - 47m2\nNguyên bản ( rèm, giàn phơi, nóng lạnh, điều hoà) 7-7.5tr/m2\nĐồ cơ bản 7.5\nFull đồ 8,5-9tr- 10tr\n\nCăn 2PN - 1WC hoặc 2PN-2WC (54m² 57m² 64m²)\nNguyên bản ( rèm, giàn phơi, nóng lạnh, điều hoà) 8tr\nĐồ cơ bản ( bếp, tủ bếp, điều hoà, nóng lạnh, tủ quần áo) 8.5-9tr\nFull đồ 9tr-10tr-11tr-13tr\n\nCăn 3PN - 2WC (75m² - 84m² - 94m²)\nNguyên bản ( rèm, giàn phơi, nóng lạnh, điều hoà) 10tr-11tr\nĐồ cơ bản ( bếp, tủ bếp, điều hoà, nóng lạnh, tủ quần áo) 14tr\nFull đồ 13tr - 18tr\n\nĐiện EVN nhà nước.\nNước tính theo giá chủ đầu tư.\nGửi xe máy 54k/tháng.\nGửi ô tô 1tr450/tháng.\n\nDịch vụ được miễn phí: Bể bơi, phòng gyms , sân tennis, sân cầu lông, sân bóng rổ, vườn dạo bộ, khu nướng BBQ, sân chơi trẻ em, máy tập ngoài trời..",
  "price": 11000000,
  "area_m2": 121,
  "price_per_m2": 90909.09090909091,
  "region": "Hà Nội",
  "district": "Quận Nam Từ Liêm",
  "ward": "Phường Tây Mỗ",
  "street": "Đại Mỗ",
  "lat": 21.01006,
  "lng": 105.7404,
  "property_type": null,
  "category": 1010,
  "post_time": 1765091942000,
  "images": 10
}