{
  "id": 128229828,
  "title": "Bán biệt thự Phú Lương Quận Hà Đông 500m, ngay vườn hồng, giá Đầu tư",
  "description": "CẬP NHẬT QUĨ CĂN BIỆT THỰ PHÚ LƯƠNG_ BIỆT THỰ QUẬN HÀ ĐÔNG _ GIÁ ***\n *  Biệt thự Mặt Hồ 220m, MT 10m, giá 39 tỷ 9\n_ Biệt thự ngay hồ, hoàn thiện thang máy, sang xịn, nhỉnh 40 tỷ\n _ Biệt thự Vườn hồng. 240m, mt 12m, nhỉnh 40 tỷ\n_ Biệt thự 200m, hoàn thiện tâm huyết, nhỉnh 30 tỷ\n_ Biệt thự mặt đường đôi, trục toà lâu đài 49.9 tỷ\n_ Biệt thự mặt vườn hoa,trung tâm thương mại, đường 18m giá 180triệu/ m2\n_ Cặp biệt thự đơn lập Phú Lương 660m, giá 179triệu/m2\n_ Biệt thự 235m, mt12.5m thô\n\n * Em có nhiều vị trí đẹp, nhà thô và hoàn thiện. Nhiều vị trí khác nhau: vườn hoa, trung tâm thương mại, mặt hồ, ngay công viên 100ha Văn Phú\n * Giao thông thuận tiện, nối các tuyến đường Quang Trung, đường Văn Khê, đường Lê Trọng Tấn. Hàng xóm khu đô thị Văn Phú, với nhiều biệt thự Văn Phú sang đẹp.\n * Biệt thự Phú Lương là một trong những biệt thự Hà Đông đáng để đầu tư sinh lời cao\n\n* Pháp lý: chuẩn giao dịch ngay\n\nLiên hệ Em Oanh *** chuyên bán biệt thự Hà Đông, bán biệt thự Quận Hà Đông 200m2 đến 500m2",
  "price": 39900000000,
  "area_m2": 86,
  "price_per_m2": 463953488.372093,
  "region": "Hà Nội",
  "district": "Quận Hà Đông",
  "ward": "Phường Phú Lương",
  "street": "Kiến Hưng",
  "lat": 20.94998,
  "lng": 105.76996,
  "property_type": null,
  "category": 1020,
  "post_time": 1765112669000,
  "images": 3
}