{
  "id": 129532396,
  "title": "Bán nhà mặt phố KĐT Đền Lừ, 85m2, 6 tầng, thang máy, kinh doanh đỉnh",
  "description": "1 MẶT PHỐ 1 MẶT NGÕ Ô TÔ TRÁNH NHAU _ 6 TẦNG _ THANG MÁY _ KINH DOANH_ VIEW HỒ \n\n- Vị trí đắc địa, khu vực sầm uất, kinh doanh tấp lập ngày đêm.\n\n- Thiết kế: \n\n+ Tầng 1,2 Mặt phố cho thuê , thang máy, thang bộ, wc giữa - Mặt ngõ sau để xe ô tô quay đầu.\n\n+ Tầng 2  1 Phòng - Bếp  WC. Tầng 3  1Phòng khách 1 ngủ  Tầng 4  : 2 ngủ Wc Tầng 5 Thờ  -  sân phơi  Tâng 6:  1  phòng rộng.\n\n- Sổ đỏ  chính chủ",
  "price": 64900000000,
  "area_m2": 80,
  "price_per_m2": 811250000.0,
  "region": "Hà Nội",
  "district": "Quận Hoàng Mai",
  "ward": "Phường Hoàng Văn Thụ",
  "street": "Đền Lừ",
  "lat": 20.98437,
  "lng": 105.86084,
  "property_type": null,
  "category": 1020,
  "post_time": 1765092486000,
  "images": 7
}