{
  "id": 129530819,
  "title": "BÁN NHÀ 6 TẦNG DÂN XÂY - GẦN PHỐ - Ô TÔ ĐỖ CỬA VÀO NHÀ  - FULL NỘI THẤ",
  "description": "BÁN NHÀ 6 TẦNG DÂN XÂY - GẦN PHỐ - Ô TÔ ĐỖ CỬA VÀO NHÀ  - FULL NỘI THẤT CAO CẤP.\n\n- Vị trí : Đẹp nhất khu vực, vài bước ra phố Thạch Bàn, Chợ Thạch Bàn,  TTTM AeonMall,  Cầu Vĩnh Tuy, TT Hành chính mới.\n\n+ Nhà 6 tầng, thiết kế đẹp, chủ tâm huyết, mặt tiền rộng thoáng, full nội thất cao cấp.\n- Thiết kế :\n- Tầng 1 : Để xe + bếp + phòng ăn.\n- Tầng 2 : Khách siêu rộng chill.\n- Tầng 3,4,5 :  Phòng ngủ Master.\n- Tầng 6: thờ + sân phơi\n\n+ Sổ đỏ cất két sẵn sàng sang tên",
  "price": 10850000000,
  "area_m2": 81,
  "price_per_m2": 133950617.28395061,
  "region": "Hà Nội",
  "district": "Quận Long Biên",
  "ward": "Phường Thạch Bàn",
  "street": "Phường Thạch Bàn",
  "lat": 21.02167,
  "lng": 105.91418,
  "property_type": null,
  "category": 1020,
  "post_time": 1765087762000,
  "images": 5
}