{
  "id": 129500679,
  "title": "Bán Nhà Bằng B Hoàng Liệt DT36m 5T Ngõ Rộng 2 Mặt Thoáng 10m Ra Ô Tô",
  "description": "SIÊU PHẨM BẰNG B - HOÀNG LIỆT \n💥 Anh Hội hàng xóm gửi bán hộ căn nhà tự xây thiết kế - Dt 36m- 5 tầng - 4 ngủ - 2 Thoáng vĩnh viễn - Ngõ Thông Gần Ô tô  - bãi gửi ô tô cách 30m - Kinh doanh nhỏ : Giá chỉ 7,45 tỷ 💥\n \n✅Vị trí khu dân cư sầm uất , gần trường chợ  , cấp 1,2 ,3 Linh Đàm \n✅Tiện ích kđt Linh Đàm 500m bến xe nước ngầm giao thông thuận tiện.\n\n📕Sổ vuông vắn , pháp lý chuẩn \n☎️Lh Zalo e điệp *** gặp chính chủ  xem nhà 24/7",
  "price": 7450000000,
  "area_m2": 80,
  "price_per_m2": 93125000.0,
  "region": "Hà Nội",
  "district": "Quận Hoàng Mai",
  "ward": "Phường Hoàng Liệt",
  "street": "Phố Bằng B",
  "lat": 20.957077,
  "lng": 105.82676,
  "property_type": null,
  "category": 1020,
  "post_time": 1765084373000,
  "images": 5
}