{
  "id": 129508560,
  "title": "Cho thuê nhà, Vỉa hè, THANG MÁY, PCCC, 99m2- 5T, P. Chùa Láng_54 Tr",
  "description": "Gia Đình tôi cho thuê nhà ; Nhà hàng, KD, VP, Vỉa hè, THANG MÁY, PCCC, Diện tích 99m2- 5 tầng, giá: 54 Triệu; P. Chùa Láng. \n+ Liên hệ trực tiếp chủ nhà: ***\n+ Vỉa hè lớn, mặt tiền rộng, Lô góc, 2 mặt tiền, thoáng.\n+ Nội thất thiết bị mới, cao cấp, hiện đại, thang máy. \n+ Vị trí gần ngay ngã ba, khu đông dân cư, kinh doanh sầm uất, nhiều văn phòng, công ty. \n+ Phù hợp VĂN PHÒNG, NHÀ HÀNG, KINH DOANH.\n+ Thuận tiện ra phố Đường Láng, Pháo Đài Láng, Nguyễn Chí Thanh, La Thành, Kim Mã, Huỳnh Thúc Kháng, Nguyên Hồng\nThông ra tuyến đường Đường Cầu Giấy, Quan Hoa, Đường Bưởi, Nguyễn Khang, Trần Duy Hưng\nDễ dàng di chuyển đến Hateco Laroma, Hong Kong Tower, Tòa nhà Icon 4 Tower\nNgay gần Âm Nhạc Quốc Gia Việt Nam, Y, Ngân Hàng, Luật, Mỹ Thuật Công Nghiệp, Ngoại Thương, Văn Hóa, Hành Chính Và Quản Trị Công, Ngoại Giao, Phụ Nữ Việt Nam, Thanh Thiếu Niên Việt Nam, Công Đoàn, Thủy Lợi, Giao Thông Vận Tải, Đống Đa, Lê Quý Đôn, Phan Huy Chú, \nTiện đi ra Vincom Center Nguyễn Chí Thanh, Trường Đại Học Luật Hà Nội, Trường Đại học Ngoại thương, Học viện Ngoại giao, Trường Đại Học Giao Thông Vận Tải, Học Viện Thanh Thiếu Niên Việt Nam\n+ Liên hệ chính chủ : ***",
  "price": 54000000,
  "area_m2": 75,
  "price_per_m2": 720000.0,
  "region": "Hà Nội",
  "district": "Quận Đống Đa",
  "ward": "Phường Láng Thượng",
  "street": "Đường Chùa Láng",
  "lat": 21.022726,
  "lng": 105.809746,
  "property_type": null,
  "category": 1030,
  "post_time": 1765074604000,
  "images": 3
}