{
  "id": 129508131,
  "title": "Cho thuê nhà, Quang Trung, Vỉa hè, Thang máy, pccc, 76m2x 6T *36 Tr",
  "description": "Mình chủ nhà cho thuê nhà  KD, VP, Nhà Hàng , Vỉa hè, Thang máy, pccc, Diện tích 76m2 x 6 tầng, giá: 36 Triệu. Quang Trung. Liên hệ  chủ nhà: ***\n. Vị trí gần ngã ba, khu đông dân cư, kinh doanh sầm uất, nhiều trụ sở văn phòng, công ty. \n. Vỉa hè lớn, mặt tiền rộng, lô góc, 2 mặt tiền, thoáng\n. Nội thất thiết bị mới, cao cấp, hiện đại, thang máy. \n. Phù hợp văn phòng, KINH DOANH, nhà hàng.\n. Thuận tiện ra phố  Trần Xuân Soạn, Lê Duẩn, Phố Huế, Bà Triệu, Mai Hắc Đế, Triệu Việt Vương, Lê Đại Hành, Bùi Thị Xuân, Nguyễn Đỉnh Chiểu, Tuệ Tĩnh, Tô Hiến Thành\nThông ra tuyến đường Nguyễn Du, Quang Trung, Trần Quốc Toản, Hàm Long, Yết Kiêu, Nguyễn công Trứ, Lò Đúc, Hòa Mã\nDễ dàng di chuyển đến Hoàng Thành\nNgay gần Dược, Mỹ Thuật Việt Nam, Trần Phú, Việt Đức, \n. Liên hệ trực tiếp chính chủ : ***",
  "price": 36000000,
  "area_m2": 73,
  "price_per_m2": 493150.68493150687,
  "region": "Hà Nội",
  "district": "Quận Hoàn Kiếm",
  "ward": "Phường Trần Hưng Đạo",
  "street": "Phố Quang Trung",
  "lat": 21.019577,
  "lng": 105.84781,
  "property_type": null,
  "category": 1030,
  "post_time": 1765098241000,
  "images": 3
}