{
  "id": 128584944,
  "title": "Gần Shophouse Sun Group và KDT Hut Mê Linh 200tr/m và KCN Quang Minh",
  "description": "Em Tuấn Nội Bài nói không với đăng tin ảo\nNgười thân cần bán\nZL em 985 va022 va007\n\nEm nói qua về Lô đất ạ:\n+ Lô đất chỉ cách Khu đô thi Hut Mê Linh có 1km đang bán 200tr/m và dự án Shophouse của SunGroup sắp làm \n\n+ Gần ngay KCN Quang Minh đông đúc\n\n+ Đất 2 mặt tiền rất đẹp, giao thông thuận lợi, giá lại rất đẹp trong khi giá xung quanh cao hơn nhiều rồi..gia đình cần bán sớm nên giá đẹp\n\n+ Sổ đỏ sẵn sàng giao dịch, đất không vướng quy hoạch ạ\n\n+ Full thổ cư 67m rất đẹp..rất vừa tiền cho ace đầu tư sinh lời cao",
  "price": 3650000000,
  "area_m2": 124,
  "price_per_m2": 29435483.870967742,
  "region": "Hà Nội",
  "district": "Huyện Mê Linh",
  "ward": "Thị trấn Quang Minh",
  "street": "Gần KCN Và KDT HUT Và Sungroup",
  "lat": 21.19158,
  "lng": 105.77326,
  "property_type": null,
  "category": 1040,
  "post_time": 1765112215000,
  "images": 6
}