{
  "id": 116040076,
  "title": "Cần bán gấp CHCC Imperia Sky Garden 423 Minh Khai, 2pn, 2wc",
  "description": "Tôi là chủ nhà cần Bán căn hộ 2PN Imperia Sky Garden, căn hộ 1511, view cây xanh\n- Diện tích thông thủy: 76m² thiết kế 2PN, 2WC.\n- Nội thất cao cấp đẹp nhất dự án,\n- Giá bán: 8,2 tỷ , xem nhà lúc nào cũng được, miễn trung gian.",
  "price": 8200000000,
  "area_m2": 76,
  "price_per_m2": 107894736.84210527,
  "region": "Hà Nội",
  "district": "Quận Hai Bà Trưng",
  "ward": "Phường Vĩnh Tuy",
  "street": "Vĩnh Tuy",
  "lat": 21.00178,
  "lng": 105.87404,
  "property_type": null,
  "category": 1010,
  "post_time": 1765111307000,
  "images": 3
}