{
  "id": 129531811,
  "title": "An cư đón Tết!!!",
  "description": "Bán nhà 48m² ngõ 99/110 Định Công Hạ, Hoàng Mai.\nNhà thoáng 2 mặt, ngõ rộng 3m; thiết kế 2 phòng ngủ, 2 wc, sạch đẹp vào ở ngay.\nGiấy tờ đất minh bạch, giao dịch vi bằng.\nGiá hơn 3 tỷ.\nLiên hệ chính chủ: ***.",
  "price": 3000000000,
  "area_m2": 80,
  "price_per_m2": 37500000.0,
  "region": "Hà Nội",
  "district": "Quận Hoàng Mai",
  "ward": "Phường Định Công",
  "street": "Ngách 99/110 Phố Định Công Hạ",
  "lat": 20.978958,
  "lng": 105.826805,
  "property_type": null,
  "category": 1020,
  "post_time": 1765090816000,
  "images": 3
}